montepy/__init__.py
montepy/__main__.py
montepy/_cell_data_control.py
montepy/_singleton.py
montepy/_version.py
montepy/cell.py
montepy/cells.py
montepy/constants.py
montepy/errors.py
montepy/exceptions.py
montepy/geometry_operators.py
montepy/materials.py
montepy/mcnp_object.py
montepy/mcnp_problem.py
montepy/numbered_mcnp_object.py
montepy/numbered_object_collection.py
montepy/particle.py
montepy/surface_collection.py
montepy/transforms.py
montepy/universe.py
montepy/universes.py
montepy/utilities.py
montepy/_scripts/__init__.py
montepy/_scripts/change_to_ascii.py
montepy/data_inputs/__init__.py
montepy/data_inputs/cell_modifier.py
montepy/data_inputs/data_input.py
montepy/data_inputs/data_parser.py
montepy/data_inputs/element.py
montepy/data_inputs/fill.py
montepy/data_inputs/importance.py
montepy/data_inputs/isotope.py
montepy/data_inputs/lattice.py
montepy/data_inputs/lattice_input.py
montepy/data_inputs/material.py
montepy/data_inputs/material_component.py
montepy/data_inputs/mode.py
montepy/data_inputs/nuclide.py
montepy/data_inputs/thermal_scattering.py
montepy/data_inputs/transform.py
montepy/data_inputs/universe_input.py
montepy/data_inputs/volume.py
montepy/input_parser/__init__.py
montepy/input_parser/block_type.py
montepy/input_parser/cell_parser.py
montepy/input_parser/data_parser.py
montepy/input_parser/input_file.py
montepy/input_parser/input_reader.py
montepy/input_parser/input_syntax_reader.py
montepy/input_parser/material_parser.py
montepy/input_parser/mcnp_input.py
montepy/input_parser/parser_base.py
montepy/input_parser/read_parser.py
montepy/input_parser/shortcuts.py
montepy/input_parser/surface_parser.py
montepy/input_parser/syntax_node.py
montepy/input_parser/tally_parser.py
montepy/input_parser/tally_seg_parser.py
montepy/input_parser/thermal_parser.py
montepy/input_parser/tokens.py
montepy/surfaces/__init__.py
montepy/surfaces/axis_plane.py
montepy/surfaces/cylinder_on_axis.py
montepy/surfaces/cylinder_par_axis.py
montepy-1.1.3.dist-info/licenses/AUTHORS
montepy-1.1.3.dist-info/licenses/LICENSE
montepy-1.1.3.dist-info/METADATA
montepy-1.1.3.dist-info/WHEEL
montepy-1.1.3.dist-info/entry_points.txt
montepy-1.1.3.dist-info/top_level.txt
montepy-1.1.3.dist-info/RECORD
