Metadata-Version: 2.4
Name: montepy
Version: 1.1.3
Summary: A library for reading, editing, and writing MCNP input files
Author-email: Micah Gale <mgale@montepy.org>, Travis Labossiere-Hickman <Travis.LabossiereHickman@inl.gov>, Brenna Carbno <brenna.carbno@inl.gov>, Benjaminas Marcinkevicius <BenjaminasDev@outlook.com>, Paul Ferney <Paul.Ferney@inl.gov>, Digvijay Yeware <yewaredigvijay@gmail.com>
Maintainer-email: Micah Gale <mgale@montepy.org>
License-Expression: MIT
Project-URL: Homepage, https://www.montepy.org/
Project-URL: Repository, https://github.com/idaholab/MontePy.git
Project-URL: Documentation, https://www.montepy.org/
Project-URL: Bug Tracker, https://github.com/idaholab/MontePy/issues
Project-URL: Changelog, https://www.montepy.org/en/stable/changelog.html
Keywords: MCNP,neutronics,imcnp,input file,monte carlo,radiation transport
Classifier: Development Status :: 4 - Beta
Classifier: Intended Audience :: Science/Research
Classifier: Intended Audience :: Developers
Classifier: Natural Language :: English
Classifier: Operating System :: OS Independent
Classifier: Topic :: Scientific/Engineering :: Physics
Classifier: Topic :: Scientific/Engineering
Classifier: Topic :: Scientific/Engineering :: Human Machine Interfaces
Classifier: Programming Language :: Python :: 3 :: Only
Classifier: Programming Language :: Python :: 3.9
Classifier: Programming Language :: Python :: 3.10
Classifier: Programming Language :: Python :: 3.11
Classifier: Programming Language :: Python :: 3.12
Classifier: Programming Language :: Python :: 3.13
Requires-Python: >=3.9
License-File: LICENSE
License-File: AUTHORS
Requires-Dist: numpy>=1.18
Requires-Dist: sly<=0.5,>=0.4
Provides-Extra: test
Requires-Dist: coverage[toml]>=6.3.2; extra == "test"
Requires-Dist: hypothesis; extra == "test"
Requires-Dist: pytest; extra == "test"
Requires-Dist: pytest-profiling; extra == "test"
Requires-Dist: montepy[build]; extra == "test"
Requires-Dist: phmutest; extra == "test"
Provides-Extra: doc
Requires-Dist: sphinx>=7.4.0; extra == "doc"
Requires-Dist: sphinxcontrib-apidoc; extra == "doc"
Requires-Dist: pydata_sphinx_theme; extra == "doc"
Requires-Dist: sphinx-favicon; extra == "doc"
Requires-Dist: sphinx-copybutton; extra == "doc"
Requires-Dist: sphinx_autodoc_typehints; extra == "doc"
Requires-Dist: autodocsumm; extra == "doc"
Provides-Extra: format
Requires-Dist: black~=25.1; extra == "format"
Provides-Extra: build
Requires-Dist: build; extra == "build"
Requires-Dist: setuptools>=64.0.0; extra == "build"
Requires-Dist: setuptools-scm>=8; extra == "build"
Provides-Extra: develop
Requires-Dist: montepy[doc,format,test]; extra == "develop"
Provides-Extra: demos
Requires-Dist: jupyter; extra == "demos"
Requires-Dist: ipykernel~=6.0; extra == "demos"
Provides-Extra: demo-test
Requires-Dist: montepy[demos]; extra == "demo-test"
Requires-Dist: papermill; extra == "demo-test"
Provides-Extra: demo-present
Requires-Dist: montepy[demos]; extra == "demo-present"
Requires-Dist: jupyterlab-rise; extra == "demo-present"
Dynamic: license-file
